xasche/__init__.py
xasche/engines/docker.py
xasche/engines/slurm.py
xasche-0.0.0.dev0.dist-info/METADATA
xasche-0.0.0.dev0.dist-info/WHEEL
xasche-0.0.0.dev0.dist-info/RECORD
